hyfit/__cli__.py
hyfit/__init__.py
hyfit/_version.py
hyfit/conf/__init__.py
hyfit/conf/about/hyfit.yaml
hyfit/py.typed
hyfi_template-0.6.10.dist-info/LICENSE
hyfi_template-0.6.10.dist-info/METADATA
hyfi_template-0.6.10.dist-info/WHEEL
hyfi_template-0.6.10.dist-info/entry_points.txt
hyfi_template-0.6.10.dist-info/RECORD
