Metadata-Version: 2.1
Name: hyfi-template
Version: 0.6.10
Summary: A GitHub Template Repository for HyFI-based Projects
Home-page: https://hyfi-template.entelecheia.ai
License: MIT
Author: Young Joon Lee
Author-email: entelecheia@hotmail.com
Requires-Python: >=3.9,<=3.12
Classifier: License :: OSI Approved :: MIT License
Classifier: Programming Language :: Python :: 3
Classifier: Programming Language :: Python :: 3.9
Classifier: Programming Language :: Python :: 3.10
Classifier: Programming Language :: Python :: 3.11
Classifier: Programming Language :: Python :: 3.12
Requires-Dist: hyfi (>=1.35.1,<2.0.0)
Project-URL: Repository, https://github.com/entelecheia/hyfi-template
